{"version": "1", "message": "ERROR: Hidden Testcases server unreachable.", "problem_id": "ads1_remedial_3_a1_1", "user_id": "chinuteja", "score": {"sample": {"0": {"execution_time": 0.45180296897888184, "passed": true}, "1": {"execution_time": 0.46483659744262695, "passed": false}, "2": {"execution_time": 0.34308314323425293, "passed": true}, "3": {"execution_time": 0.4672970771789551, "passed": false}, "4": {"execution_time": 0.5870037078857422, "passed": true}, "5": {"execution_time": 0.47126007080078125, "passed": true}, "6": {"execution_time": 0.44394588470458984, "passed": false}}}, "check_style_score": "0/1"}